nifty_solve/__init__.py
nifty_solve/jax_operators.py
nifty_solve/operators.py
nifty_solve/utils.py
nifty_solve-0.1.2.dist-info/METADATA
nifty_solve-0.1.2.dist-info/WHEEL
nifty_solve-0.1.2.dist-info/top_level.txt
nifty_solve-0.1.2.dist-info/RECORD
