Metadata-Version: 2.4
Name: nifty-solve
Version: 0.1.2
Summary: Nifty solver
Author-email: Andy Casey <andrew.casey@monash.edu>, Thomas Hilder <thomas.hilder@monash.edu>
Maintainer-email: Andy Casey <andrew.casey@monash.edu>
License: LICENSE.md
Keywords: astronomy software
Requires-Python: >=3.9
Requires-Dist: numpy
Requires-Dist: finufft
Requires-Dist: pylops
Requires-Dist: scipy
Provides-Extra: dev
Requires-Dist: pytest; extra == "dev"
Requires-Dist: pytest-cov; extra == "dev"
Requires-Dist: pytest-sugar; extra == "dev"
Requires-Dist: pre-commit; extra == "dev"
Requires-Dist: black; extra == "dev"
Provides-Extra: jax
Requires-Dist: jax; extra == "jax"
Requires-Dist: jax-finufft; extra == "jax"
